ldpc/__init__.pxd
ldpc/__init__.py
ldpc/alist.py
ldpc/protograph.py
ldpc/py.typed
ldpc/_legacy_ldpc_v1/__init__.py
ldpc/_legacy_ldpc_v1/_legacy_bp_decoder.py
ldpc/_legacy_ldpc_v1/_legacy_bposd_decoder.py
ldpc/belief_find_decoder/__init__.pxd
ldpc/belief_find_decoder/__init__.py
ldpc/belief_find_decoder/__init__.pyi
ldpc/belief_find_decoder/_belief_find_decoder.cpp
ldpc/belief_find_decoder/_belief_find_decoder.cpython-313-aarch64-linux-gnu.so
ldpc/belief_find_decoder/_belief_find_decoder.pxd
ldpc/belief_find_decoder/_belief_find_decoder.pyx
ldpc/bp_decoder/__init__.pxd
ldpc/bp_decoder/__init__.py
ldpc/bp_decoder/__init__.pyi
ldpc/bp_decoder/_bp_decoder.cpp
ldpc/bp_decoder/_bp_decoder.cpython-313-aarch64-linux-gnu.so
ldpc/bp_decoder/_bp_decoder.pxd
ldpc/bp_decoder/_bp_decoder.pyx
ldpc/bp_decoder/py.typed
ldpc/bp_decoder/to_pyi.py
ldpc/bp_flip/__init__.pxd
ldpc/bp_flip/__init__.py
ldpc/bp_flip/__init__.pyi
ldpc/bp_flip/_bp_flip.cpp
ldpc/bp_flip/_bp_flip.cpython-313-aarch64-linux-gnu.so
ldpc/bp_flip/_bp_flip.pxd
ldpc/bp_flip/_bp_flip.pyx
ldpc/bp_flip/py.typed
ldpc/bplsd_decoder/__init__.pxd
ldpc/bplsd_decoder/__init__.py
ldpc/bplsd_decoder/__init__.pyi
ldpc/bplsd_decoder/_bplsd_decoder.cpp
ldpc/bplsd_decoder/_bplsd_decoder.cpython-313-aarch64-linux-gnu.so
ldpc/bplsd_decoder/_bplsd_decoder.pxd
ldpc/bplsd_decoder/_bplsd_decoder.pyx
ldpc/bplsd_decoder/py.typed
ldpc/bposd_decoder/__init__.pxd
ldpc/bposd_decoder/__init__.py
ldpc/bposd_decoder/__init__.pyi
ldpc/bposd_decoder/_bposd_decoder.cpp
ldpc/bposd_decoder/_bposd_decoder.cpython-313-aarch64-linux-gnu.so
ldpc/bposd_decoder/_bposd_decoder.pxd
ldpc/bposd_decoder/_bposd_decoder.pyx
ldpc/bposd_decoder/py.typed
ldpc/ckt_noise/__init__.py
ldpc/ckt_noise/base_overlapping_window_decoder.py
ldpc/ckt_noise/bipartite_edge_coloring.py
ldpc/ckt_noise/bposd_overlapping_window.py
ldpc/ckt_noise/config.py
ldpc/ckt_noise/css_code_memory_circuit.py
ldpc/ckt_noise/dem_matrices.py
ldpc-2.4.1.dist-info/METADATA
ldpc-2.4.1.dist-info/WHEEL
ldpc-2.4.1.dist-info/top_level.txt
ldpc-2.4.1.dist-info/RECORD
ldpc-2.4.1.dist-info/licenses/LICENSE
