Metadata-Version: 2.4
Name: ldpc
Version: 2.4.1
Summary: LDPC: Python Tools for Low Density Parity Check Codes
Author-email: Joschka Roffe <joschka@roffe.eu>
License: MIT License
Project-URL: Documentation, https://software.roffe.eu/ldpc
Classifier: Development Status :: 4 - Beta
Requires-Python: >=3.10
License-File: LICENSE
Requires-Dist: numpy>=1.24.0
Requires-Dist: scipy>=1.9.3
Requires-Dist: tqdm
Requires-Dist: pytest
Requires-Dist: stim
Requires-Dist: sinter>=1.12.0
Requires-Dist: pymatching
Dynamic: license-file
